nso_bridge/__init__.py
nso_bridge/metadata.py
nso_bridge/nsa.py
nso_bridge/nso.py
nso_bridge/utils.py
nso_bridge/models/__init__.py
nso_bridge/models/accounts.py
nso_bridge/models/imink.py
nso_bridge-0.1.7.dist-info/LICENSE
nso_bridge-0.1.7.dist-info/WHEEL
nso_bridge-0.1.7.dist-info/METADATA
nso_bridge-0.1.7.dist-info/RECORD
