Metadata-Version: 2.1
Name: nso-bridge
Version: 0.1.7
Summary: Nintendo Switch Online API bridge (for Nintendo Switch Online API wrapper)
Keywords: Nintendo,Nintendo Switch,Nintendo Switch Online,Nintendo Switch Online API
Author-email: zeroday0619 <zeroday0619_dev@outlook.com>
Classifier: License :: OSI Approved :: MIT License
Requires-Dist: requests >= 2.28.1
Requires-Dist: keyring >= 23.9.1
Requires-Dist: beautifulsoup4 >= 4.11.1
Requires-Dist: pydantic>=1.10.2
Requires-Dist: black>=22.3.0 ; extra == "lint"
Requires-Dist: flake8>=4.0.1 ; extra == "lint"
Requires-Dist: isort>=5.10.1 ; extra == "lint"
Requires-Dist: autoflake>=1.5.3 ; extra == "lint"
Requires-Dist: pytest >= 7.1.3 ; extra == "test"
Requires-Dist: pytest-cov >= 3.0.0 ; extra == "test"
Project-URL: Home, https://github.com/zeroday0619/Nintendo_Switch_Online_API_Bridge
Provides-Extra: lint
Provides-Extra: test
